inferpro/__init__.py
inferpro/example.py
inferpro-0.0.5.dist-info/licenses/LICENSE
inferpro-0.0.5.dist-info/METADATA
inferpro-0.0.5.dist-info/WHEEL
inferpro-0.0.5.dist-info/top_level.txt
inferpro-0.0.5.dist-info/RECORD
