Metadata-Version: 2.4
Name: inferpro
Version: 0.0.5
Summary: Inference Profiler for profiling and benchmarking Machine Learning models
Author-email: Vidyatheerthan <vidyatheerthan@gmail.com>
License-Expression: MIT
Project-URL: Homepage, https://github.com/projectindica/inferpro
Project-URL: Issues, https://github.com/projectindica/inferpro
Classifier: Programming Language :: Python :: 3
Classifier: Operating System :: OS Independent
Requires-Python: >=3.9
License-File: LICENSE
Dynamic: license-file
